misty2py_skills/__init__.py
misty2py_skills/demonstrations/__init__.py
misty2py_skills/demonstrations/battery_printer.py
misty2py_skills/demonstrations/explore.py
misty2py_skills/expressions.py
misty2py_skills/face_recognition.py
misty2py_skills/hey_misty.py
misty2py_skills/question_answering.py
misty2py_skills/remote_control.py
misty2py_skills-2.0.1.dist-info/LICENSE
misty2py_skills-2.0.1.dist-info/METADATA
misty2py_skills-2.0.1.dist-info/WHEEL
misty2py_skills-2.0.1.dist-info/RECORD
