Metadata-Version: 2.3
Name: misty2py-skills
Version: 2.0.1
Summary: A Python library of Misty II skills developed using Misty2py library
License: MIT
Author: Chris 'Scar(R)ed' Vajdík
Author-email: chrisquackless@duck.com
Requires-Python: >=3.10
Classifier: Programming Language :: Python :: 3
Classifier: License :: OSI Approved :: MIT License
Classifier: Operating System :: OS Independent
Requires-Dist: deprecated (>=1.2.18,<2.0.0)
Requires-Dist: keyboard (>=0.13.5,<0.14.0)
Requires-Dist: misty2py (>=5.0.1,<6.0.0)
Requires-Dist: num2words (>=0.5.14,<0.6.0)
Requires-Dist: pymitter (>=1.0.0,<2.0.0)
Requires-Dist: pynput (>=1.8.0,<2.0.0)
Requires-Dist: python-dotenv (>=1.0.1,<2.0.0)
Requires-Dist: speechrecognition (>=3.14.1,<4.0.0)
Project-URL: Documentation, https://misty2py-skills-documentation.onrender.com/
Project-URL: Repository, https://gitlab.com/scarred-libraries/misty2py-skills
